odoo/addons/edi_voxel_sale_order_import/README.rst
odoo/addons/edi_voxel_sale_order_import/__init__.py
odoo/addons/edi_voxel_sale_order_import/__manifest__.py
odoo/addons/edi_voxel_sale_order_import/data/ir_cron_data.xml
odoo/addons/edi_voxel_sale_order_import/i18n/edi_voxel_sale_order_import.pot
odoo/addons/edi_voxel_sale_order_import/i18n/es.po
odoo/addons/edi_voxel_sale_order_import/models/__init__.py
odoo/addons/edi_voxel_sale_order_import/models/res_company.py
odoo/addons/edi_voxel_sale_order_import/models/res_config_settings.py
odoo/addons/edi_voxel_sale_order_import/models/sale_order.py
odoo/addons/edi_voxel_sale_order_import/readme/CONFIGURE.rst
odoo/addons/edi_voxel_sale_order_import/readme/CONTRIBUTORS.rst
odoo/addons/edi_voxel_sale_order_import/readme/DESCRIPTION.rst
odoo/addons/edi_voxel_sale_order_import/readme/USAGE.rst
odoo/addons/edi_voxel_sale_order_import/security/ir.model.access.csv
odoo/addons/edi_voxel_sale_order_import/security/voxel_sale_order_security.xml
odoo/addons/edi_voxel_sale_order_import/static/description/icon.png
odoo/addons/edi_voxel_sale_order_import/static/description/index.html
odoo/addons/edi_voxel_sale_order_import/tests/__init__.py
odoo/addons/edi_voxel_sale_order_import/tests/test_voxel_sale_order_import.py
odoo/addons/edi_voxel_sale_order_import/tests/voxel_xml/Pedido_20190619_145750_0611125750634.xml
odoo/addons/edi_voxel_sale_order_import/views/res_company_views.xml
odoo/addons/edi_voxel_sale_order_import/views/res_config_settings_views.xml
odoo/addons/edi_voxel_sale_order_import/views/sale_order_views.xml
odoo13_addon_edi_voxel_sale_order_import-13.0.1.0.7.dist-info/METADATA
odoo13_addon_edi_voxel_sale_order_import-13.0.1.0.7.dist-info/WHEEL
odoo13_addon_edi_voxel_sale_order_import-13.0.1.0.7.dist-info/top_level.txt
odoo13_addon_edi_voxel_sale_order_import-13.0.1.0.7.dist-info/RECORD
