Metadata-Version: 2.1
Name: odoo13-addon-edi-voxel-sale-order-import
Version: 13.0.1.0.7
Summary: Import sale order from Voxel.
Home-page: https://github.com/OCA/edi
Author: Tecnativa, Odoo Community Association (OCA)
Author-email: support@odoo-community.org
License: AGPL-3
Platform: UNKNOWN
Classifier: Programming Language :: Python
Classifier: Framework :: Odoo
Classifier: Framework :: Odoo :: 13.0
Classifier: License :: OSI Approved :: GNU Affero General Public License v3
Classifier: Development Status :: 5 - Production/Stable
Requires-Python: >=3.5
Requires-Dist: odoo13-addon-edi-voxel
Requires-Dist: odoo13-addon-onchange-helper
Requires-Dist: odoo (<13.1dev,>=13.0a)
